qtapputils/__init__.py
qtapputils/colors.py
qtapputils/icons.py
qtapputils/qthelpers.py
qtapputils/testing.py
qtapputils/managers/__init__.py
qtapputils/managers/capture.py
qtapputils/managers/fileio.py
qtapputils/managers/shortcuts.py
qtapputils/managers/taskmanagers.py
qtapputils/managers/tests/__init__.py
qtapputils/managers/tests/test_fileio.py
qtapputils/managers/tests/test_shortcut_manager.py
qtapputils/managers/tests/test_taskmanagers.py
qtapputils/tests/__init__.py
qtapputils/tests/test_icons.py
qtapputils/tests/test_qthelpers.py
qtapputils/utils/__init__.py
qtapputils/utils/console.py
qtapputils/utils/fileio.py
qtapputils/widgets/__init__.py
qtapputils/widgets/about.py
qtapputils/widgets/buttons.py
qtapputils/widgets/configdialog.py
qtapputils/widgets/console.py
qtapputils/widgets/dialogs.py
qtapputils/widgets/exceptions.py
qtapputils/widgets/path.py
qtapputils/widgets/range.py
qtapputils/widgets/splash.py
qtapputils/widgets/statusbar.py
qtapputils/widgets/waitingspinner.py
qtapputils/widgets/tests/__init__.py
qtapputils/widgets/tests/test_buttons.py
qtapputils/widgets/tests/test_configdialog.py
qtapputils/widgets/tests/test_path.py
qtapputils/widgets/tests/test_range.py
qtapputils/widgets/tests/test_splash.py
qtapputils/widgets/tests/test_statusbar.py
qtapputils-0.10.0.dist-info/LICENSE
qtapputils-0.10.0.dist-info/METADATA
qtapputils-0.10.0.dist-info/WHEEL
qtapputils-0.10.0.dist-info/top_level.txt
qtapputils-0.10.0.dist-info/RECORD
