Metadata-Version: 2.1
Name: qtapputils
Version: 0.10.0
Summary: Utilities for building Qt applications in Python.
Home-page: https://github.com/geo-stack/qtapputils
Author: Jean-Sébastien Gosselin
Author-email: jean-sebastien.gosselin@outlook.ca
License: MIT
Classifier: Programming Language :: Python :: 3
Classifier: License :: OSI Approved :: MIT License
Classifier: Operating System :: OS Independent
License-File: LICENSE
Provides-Extra: with-deps
Requires-Dist: qtpy ; extra == 'with-deps'
Requires-Dist: pyqt5 ; extra == 'with-deps'
Requires-Dist: matplotlib ; extra == 'with-deps'
Requires-Dist: qtawesome ; extra == 'with-deps'
